{
  "teamId": 108,
  "moves": [
    {
      "date": "2026-03-21",
      "player": "Josh Groll",
      "position": "F",
      "type": "reserve",
      "summary": "Placed on Reserve 3/20"
    },
    {
      "date": "2026-03-21",
      "player": "Noah Delmas",
      "position": "D",
      "type": "active",
      "summary": "Activated from IR 14 Day 3/20"
    },
    {
      "date": "2026-03-21",
      "player": "Blake Dangos",
      "position": "D",
      "type": "reserve",
      "summary": "Placed on Reserve"
    },
    {
      "date": "2026-03-21",
      "player": "Tian Rask",
      "position": "F",
      "type": "active",
      "summary": "Activated from Reserve"
    },
    {
      "date": "2026-03-20",
      "player": "Austen May",
      "position": "D",
      "type": "active",
      "summary": "Activated from Reserve 3/19"
    },
    {
      "date": "2026-03-18",
      "player": "True Crowe",
      "position": "D",
      "type": "ir",
      "summary": "Transferred to IR 14 Day"
    },
    {
      "date": "2026-03-18",
      "player": "Patrick Newell",
      "position": "F",
      "type": "traded",
      "summary": "Traded to Kalamazoo"
    },
    {
      "date": "2026-03-18",
      "player": "Josh Groll",
      "position": "F",
      "type": "active",
      "summary": "Acquired from Fort Wayne"
    },
    {
      "date": "2026-03-18",
      "player": "Austen May",
      "position": "D",
      "type": "reserve",
      "summary": "Placed on Reserve"
    },
    {
      "date": "2026-03-18",
      "player": "Austen May",
      "position": "D",
      "type": "signed",
      "summary": "Signed ECHL SPC"
    },
    {
      "date": "2026-03-18",
      "player": "Tian Rask",
      "position": "F",
      "type": "reserve",
      "summary": "Placed on Reserve"
    },
    {
      "date": "2026-03-18",
      "player": "Jack Seymour",
      "position": "F",
      "type": "signed",
      "summary": "Signed ECHL SPC"
    },
    {
      "date": "2026-03-17",
      "player": "Anthony Rinaldi",
      "position": "F",
      "type": "traded",
      "summary": "Traded to South Carolina"
    },
    {
      "date": "2026-03-17",
      "player": "Logan Nelson",
      "position": "F",
      "type": "traded",
      "summary": "Traded to Fort Wayne"
    },
    {
      "date": "2026-03-17",
      "player": "Tian Rask",
      "position": "F",
      "type": "active",
      "summary": "Activated from Reserve"
    },
    {
      "date": "2026-03-17",
      "player": "Nate Hanley",
      "position": "F",
      "type": "signed",
      "summary": "Signed ECHL SPC"
    },
    {
      "date": "2026-03-15",
      "player": "Tian Rask",
      "position": "F",
      "type": "suspended",
      "summary": "Suspended 2 Games"
    },
    {
      "date": "2026-03-15",
      "player": "Tian Rask",
      "position": "F",
      "type": "reserve",
      "summary": "Placed on Reserve"
    },
    {
      "date": "2026-03-15",
      "player": "Demetrios Koumontzis",
      "position": "F",
      "type": "active",
      "summary": "Activated from Reserve"
    },
    {
      "date": "2026-03-15",
      "player": "Anthony Messuri",
      "position": "F",
      "type": "active",
      "summary": "Activated from Reserve"
    }
  ]
}